exobrain/README.md
exobrain/actions/README.md
exobrain/actions/schemas/__about__.py
exobrain/actions/schemas/__init__.py
exobrain/actions/schemas/action_data.py
exobrain/actions/schemas/base_model.py
exobrain/actions/schemas/py.typed
exobrain/actions/schemas/version_info.py
exobrain_actions_schemas-0.2.0.dist-info/METADATA
exobrain_actions_schemas-0.2.0.dist-info/WHEEL
exobrain_actions_schemas-0.2.0.dist-info/licenses/LICENSE.md
exobrain_actions_schemas-0.2.0.dist-info/RECORD
