Metadata-Version: 2.4
Name: exobrain-actions-schemas
Version: 0.2.0
Summary: Pydantic models for Exobrain Actions management (REST API clients or FastAPI/Flask web services)
Project-URL: Documentation, https://github.com/arnaudmorvan-dfya/exobrain-actions-schemas#readme
Project-URL: Issues, https://github.com/arnaudmorvan-dfya/exobrain-actions-schemas/issues
Project-URL: Source, https://github.com/arnaudmorvan-dfya/exobrain-actions-schemas
Author-email: Laurent LAPORTE <laurent@dfya.io>
License: Copyright © 2025-present DFYA SAS, All rights reserved. 
License-File: LICENSE.md
Classifier: Development Status :: 4 - Beta
Classifier: License :: Other/Proprietary License
Classifier: Programming Language :: Python
Classifier: Programming Language :: Python :: 3.12
Requires-Python: >=3.12
Requires-Dist: pydantic<3,>=2.11.7
